captionalchemy/__init__.py
captionalchemy/__main__.py
captionalchemy/caption.py
captionalchemy/tools/audio_analysis/__init__.py
captionalchemy/tools/audio_analysis/audio_segment_integration.py
captionalchemy/tools/audio_analysis/diarization.py
captionalchemy/tools/audio_analysis/non_speech_detection.py
captionalchemy/tools/audio_analysis/vad.py
captionalchemy/tools/captioning/timing_analyzer.py
captionalchemy/tools/captioning/transcriber.py
captionalchemy/tools/captioning/words_dictionary.json
captionalchemy/tools/captioning/writers/sami_writer.py
captionalchemy/tools/captioning/writers/srt_writer.py
captionalchemy/tools/captioning/writers/vtt_writer.py
captionalchemy/tools/cv/embed_known_faces.py
captionalchemy/tools/cv/recognize_faces.py
captionalchemy/tools/media_utils/download_video.py
captionalchemy/tools/media_utils/extract_audio.py
captionalchemy-1.1.1.dist-info/licenses/LICENSE
captionalchemy-1.1.1.dist-info/METADATA
captionalchemy-1.1.1.dist-info/WHEEL
captionalchemy-1.1.1.dist-info/entry_points.txt
captionalchemy-1.1.1.dist-info/top_level.txt
captionalchemy-1.1.1.dist-info/RECORD
