Metadata-Version: 2.4
Name: captionalchemy
Version: 1.1.1
Summary: A Python package to create closed captions with face detection and recognition.
Author-email: Ben Batman <benbatman2@gmail.com>
License: MIT
Keywords: caption,closed captions,face detection,face recognition,video processing
Classifier: Programming Language :: Python :: 3
Classifier: License :: OSI Approved :: MIT License
Classifier: Operating System :: OS Independent
Requires-Python: >=3.10
License-File: LICENSE
Requires-Dist: pyannote.audio==3.3.2
Requires-Dist: pydub==0.25.1
Requires-Dist: openai-whisper==20240930
Requires-Dist: python-dotenv==1.1.0
Requires-Dist: opencv-python==4.11.0.86
Requires-Dist: numpy==2.1.3
Requires-Dist: protobuf==5.29.4
Requires-Dist: insightface==0.7.3
Requires-Dist: onnxruntime==1.22.0
Requires-Dist: panns-inference==0.1.1
Requires-Dist: librosa==0.11.0
Requires-Dist: tqdm==4.67.1
Requires-Dist: torch==2.7.0
Provides-Extra: dev
Requires-Dist: pytest==8.4.0; extra == "dev"
Requires-Dist: mypy==1.16.0; extra == "dev"
Requires-Dist: flake8==7.2.0; extra == "dev"
Requires-Dist: black==25.1.0; extra == "dev"
Requires-Dist: pytest-cov==6.2.1; extra == "dev"
Requires-Dist: setuptools-scm==8.3.1; extra == "dev"
Provides-Extra: cuda
Requires-Dist: onnxruntime-gpu==1.22.0; extra == "cuda"
Dynamic: license-file
